pygenray/__about__.py
pygenray/__init__.py
pygenray/eigenrays.py
pygenray/environment.py
pygenray/integration_processes.py
pygenray/launch_rays.py
pygenray/multi_processing.py
pygenray/ray_objects.py
pygenray-0.0.2.dist-info/METADATA
pygenray-0.0.2.dist-info/WHEEL
pygenray-0.0.2.dist-info/licenses/LICENSE.txt
pygenray-0.0.2.dist-info/RECORD
